{
  "actions": [
    {
      "name": "setOn",
      "description": "Set state to On",
      "parameters": [],
      "isStandard": true,
      "type": "CUSTOM"
    },
    {
      "name": "setOff",
      "description": "Set state to Off",
      "parameters": [],
      "isStandard": true,
      "type": "CUSTOM"
    }
  ],
  "fields": [
    {
      "name": "state",
      "type": "CUSTOM",
      "valueClass": "Boolean",
      "isCollection": false,
      "tags": [
        "switch"
      ]
    }
  ],
  "messageFormat": "json"
}
